components.py
currency_utils.py
socket_methods.py
ekp_sdk-0.0.2.dist-info/LICENSE
ekp_sdk-0.0.2.dist-info/METADATA
ekp_sdk-0.0.2.dist-info/WHEEL
ekp_sdk-0.0.2.dist-info/top_level.txt
ekp_sdk-0.0.2.dist-info/RECORD
