Metadata-Version: 2.1
Name: ekp-sdk
Version: 0.0.2
Summary: Python SDK for frontend components usage
Home-page: https://github.com/hiki0505/python-ekp-sdk
Author: Earn Keeper (Gavin Shaw)
Author-email: gavin@earnkeeper.io
License: UNKNOWN
Keywords: python,earnkeeper,sdk,components
Platform: UNKNOWN
Classifier: Programming Language :: Python :: 3
Classifier: Programming Language :: Python :: 3.8
Classifier: Programming Language :: Python :: 3.9
Classifier: Operating System :: OS Independent
Classifier: License :: OSI Approved :: GNU General Public License v2 or later (GPLv2+)
License-File: LICENSE
Requires-Dist: eventlet (==0.33.0)
Requires-Dist: pycoingecko (==2.2.0)
Requires-Dist: python-socketio (==5.6.0)
